[{"model": "admin.logentry", "pk": 1, "fields": {"action_time": "2023-10-27T14:38:46.135Z", "user": 1, "content_type": 7, "object_id": "1", "object_repr": "Американки", "action_flag": 1, "change_message": "[{\"added\": {}}]"}}, {"model": "admin.logentry", "pk": 2, "fields": {"action_time": "2023-10-27T14:39:04.002Z", "user": 1, "content_type": 8, "object_id": "1", "object_repr": "Alina Lopez", "action_flag": 1, "change_message": "[{\"added\": {}}]"}}, {"model": "admin.logentry", "pk": 3, "fields": {"action_time": "2023-10-27T14:40:53.368Z", "user": 1, "content_type": 7, "object_id": "2", "object_repr": "Русские", "action_flag": 1, "change_message": "[{\"added\": {}}]"}}, {"model": "admin.logentry", "pk": 4, "fields": {"action_time": "2023-10-27T14:40:58.459Z", "user": 1, "content_type": 8, "object_id": "2", "object_repr": "dollhole", "action_flag": 1, "change_message": "[{\"added\": {}}]"}}, {"model": "admin.logentry", "pk": 5, "fields": {"action_time": "2023-10-27T14:41:54.000Z", "user": 1, "content_type": 7, "object_id": "3", "object_repr": "Чешки", "action_flag": 1, "change_message": "[{\"added\": {}}]"}}, {"model": "admin.logentry", "pk": 6, "fields": {"action_time": "2023-10-27T14:41:57.004Z", "user": 1, "content_type": 8, "object_id": "3", "object_repr": "Mini Diva", "action_flag": 1, "change_message": "[{\"added\": {}}]"}}, {"model": "admin.logentry", "pk": 7, "fields": {"action_time": "2023-10-27T14:42:28.975Z", "user": 1, "content_type": 8, "object_id": "4", "object_repr": "Eva Elfie", "action_flag": 1, "change_message": "[{\"added\": {}}]"}}, {"model": "admin.logentry", "pk": 8, "fields": {"action_time": "2023-10-27T14:42:40.532Z", "user": 1, "content_type": 8, "object_id": "4", "object_repr": "Eva Elfie", "action_flag": 2, "change_message": "[{\"changed\": {\"fields\": [\"\\u041a\\u0430\\u0442\\u0435\\u0433\\u043e\\u0440\\u0438\\u044f\"]}}]"}}, {"model": "admin.logentry", "pk": 9, "fields": {"action_time": "2023-10-27T14:43:11.549Z", "user": 1, "content_type": 7, "object_id": "4", "object_repr": "Китаянки", "action_flag": 1, "change_message": "[{\"added\": {}}]"}}, {"model": "admin.logentry", "pk": 10, "fields": {"action_time": "2023-10-27T14:43:20.295Z", "user": 1, "content_type": 8, "object_id": "5", "object_repr": "Hong Kong Doll", "action_flag": 1, "change_message": "[{\"added\": {}}]"}}, {"model": "admin.logentry", "pk": 11, "fields": {"action_time": "2023-10-27T14:43:58.321Z", "user": 1, "content_type": 7, "object_id": "5", "object_repr": "Эстонки", "action_flag": 1, "change_message": "[{\"added\": {}}]"}}, {"model": "admin.logentry", "pk": 12, "fields": {"action_time": "2023-10-27T14:44:00.302Z", "user": 1, "content_type": 8, "object_id": "6", "object_repr": "Solazola", "action_flag": 1, "change_message": "[{\"added\": {}}]"}}, {"model": "admin.logentry", "pk": 13, "fields": {"action_time": "2023-10-27T14:46:38.708Z", "user": 1, "content_type": 8, "object_id": "5", "object_repr": "Hong Kong Doll", "action_flag": 2, "change_message": "[{\"changed\": {\"fields\": [\"\\u0424\\u043e\\u0442\\u043e\\u0433\\u0440\\u0430\\u0444\\u0438\\u044f\"]}}]"}}, {"model": "admin.logentry", "pk": 14, "fields": {"action_time": "2023-10-27T14:47:06.006Z", "user": 1, "content_type": 8, "object_id": "7", "object_repr": "Cherry Kiss", "action_flag": 1, "change_message": "[{\"added\": {}}]"}}, {"model": "admin.logentry", "pk": 15, "fields": {"action_time": "2023-10-27T14:47:46.336Z", "user": 1, "content_type": 8, "object_id": "8", "object_repr": "Little Caprice", "action_flag": 1, "change_message": "[{\"added\": {}}]"}}, {"model": "admin.logentry", "pk": 16, "fields": {"action_time": "2023-10-27T14:48:18.338Z", "user": 1, "content_type": 8, "object_id": "9", "object_repr": "Alex Grey", "action_flag": 1, "change_message": "[{\"added\": {}}]"}}, {"model": "admin.logentry", "pk": 17, "fields": {"action_time": "2023-10-28T19:07:44.343Z", "user": 1, "content_type": 8, "object_id": "10", "object_repr": "Rachel Rivers", "action_flag": 1, "change_message": "[{\"added\": {}}]"}}, {"model": "admin.logentry", "pk": 18, "fields": {"action_time": "2023-10-28T19:09:22.824Z", "user": 1, "content_type": 8, "object_id": "11", "object_repr": "Vanessa Decker", "action_flag": 1, "change_message": "[{\"added\": {}}]"}}, {"model": "admin.logentry", "pk": 19, "fields": {"action_time": "2023-10-28T19:11:25.539Z", "user": 1, "content_type": 8, "object_id": "12", "object_repr": "Tiffany Thompson", "action_flag": 1, "change_message": "[{\"added\": {}}]"}}, {"model": "admin.logentry", "pk": 20, "fields": {"action_time": "2023-10-28T19:13:14.599Z", "user": 1, "content_type": 8, "object_id": "13", "object_repr": "Valerie Steele", "action_flag": 1, "change_message": "[{\"added\": {}}]"}}, {"model": "admin.logentry", "pk": 21, "fields": {"action_time": "2023-10-28T19:13:58.887Z", "user": 1, "content_type": 8, "object_id": "14", "object_repr": "Lola Fae", "action_flag": 1, "change_message": "[{\"added\": {}}]"}}, {"model": "admin.logentry", "pk": 22, "fields": {"action_time": "2023-10-28T19:15:26.919Z", "user": 1, "content_type": 8, "object_id": "15", "object_repr": "Princess Clover", "action_flag": 1, "change_message": "[{\"added\": {}}]"}}, {"model": "admin.logentry", "pk": 23, "fields": {"action_time": "2023-10-28T19:16:07.068Z", "user": 1, "content_type": 8, "object_id": "16", "object_repr": "Jada Stevens", "action_flag": 1, "change_message": "[{\"added\": {}}]"}}, {"model": "admin.logentry", "pk": 24, "fields": {"action_time": "2023-10-28T19:17:43.433Z", "user": 1, "content_type": 8, "object_id": "17", "object_repr": "Amy Pink", "action_flag": 1, "change_message": "[{\"added\": {}}]"}}, {"model": "admin.logentry", "pk": 25, "fields": {"action_time": "2023-10-28T19:18:19.672Z", "user": 1, "content_type": 8, "object_id": "18", "object_repr": "Haley Reed", "action_flag": 1, "change_message": "[{\"added\": {}}]"}}, {"model": "admin.logentry", "pk": 26, "fields": {"action_time": "2023-10-28T19:19:00.286Z", "user": 1, "content_type": 8, "object_id": "19", "object_repr": "Nessa Devil", "action_flag": 1, "change_message": "[{\"added\": {}}]"}}, {"model": "admin.logentry", "pk": 27, "fields": {"action_time": "2023-10-28T19:19:35.537Z", "user": 1, "content_type": 8, "object_id": "20", "object_repr": "Katerina Hartlova", "action_flag": 1, "change_message": "[{\"added\": {}}]"}}, {"model": "admin.logentry", "pk": 28, "fields": {"action_time": "2023-10-28T19:21:46.028Z", "user": 1, "content_type": 8, "object_id": "21", "object_repr": "Riley Reid", "action_flag": 1, "change_message": "[{\"added\": {}}]"}}, {"model": "admin.logentry", "pk": 29, "fields": {"action_time": "2023-10-28T20:59:51.386Z", "user": 1, "content_type": 7, "object_id": "1", "object_repr": "Американки", "action_flag": 2, "change_message": "[{\"changed\": {\"fields\": [\"Slug\"]}}]"}}, {"model": "admin.logentry", "pk": 30, "fields": {"action_time": "2023-10-28T20:59:56.781Z", "user": 1, "content_type": 7, "object_id": "4", "object_repr": "Китаянки", "action_flag": 2, "change_message": "[{\"changed\": {\"fields\": [\"Slug\"]}}]"}}, {"model": "admin.logentry", "pk": 31, "fields": {"action_time": "2023-10-28T21:00:01.742Z", "user": 1, "content_type": 7, "object_id": "2", "object_repr": "Русские", "action_flag": 2, "change_message": "[{\"changed\": {\"fields\": [\"Slug\"]}}]"}}, {"model": "admin.logentry", "pk": 32, "fields": {"action_time": "2023-10-28T21:00:06.512Z", "user": 1, "content_type": 7, "object_id": "3", "object_repr": "Чешки", "action_flag": 2, "change_message": "[{\"changed\": {\"fields\": [\"Slug\"]}}]"}}, {"model": "admin.logentry", "pk": 33, "fields": {"action_time": "2023-10-28T21:00:11.066Z", "user": 1, "content_type": 7, "object_id": "5", "object_repr": "Эстонки", "action_flag": 2, "change_message": "[{\"changed\": {\"fields\": [\"Slug\"]}}]"}}, {"model": "admin.logentry", "pk": 34, "fields": {"action_time": "2023-10-28T21:04:11.622Z", "user": 1, "content_type": 7, "object_id": "1", "object_repr": "Американки", "action_flag": 2, "change_message": "[{\"changed\": {\"fields\": [\"Slug\"]}}]"}}, {"model": "admin.logentry", "pk": 35, "fields": {"action_time": "2023-10-28T21:04:22.737Z", "user": 1, "content_type": 7, "object_id": "4", "object_repr": "Китаянки", "action_flag": 2, "change_message": "[{\"changed\": {\"fields\": [\"Slug\"]}}]"}}, {"model": "admin.logentry", "pk": 36, "fields": {"action_time": "2023-10-28T21:04:27.597Z", "user": 1, "content_type": 7, "object_id": "2", "object_repr": "Русские", "action_flag": 2, "change_message": "[{\"changed\": {\"fields\": [\"Slug\"]}}]"}}, {"model": "admin.logentry", "pk": 37, "fields": {"action_time": "2023-10-28T21:04:31.753Z", "user": 1, "content_type": 7, "object_id": "3", "object_repr": "Чешки", "action_flag": 2, "change_message": "[{\"changed\": {\"fields\": [\"Slug\"]}}]"}}, {"model": "admin.logentry", "pk": 38, "fields": {"action_time": "2023-10-28T21:04:35.474Z", "user": 1, "content_type": 7, "object_id": "5", "object_repr": "Эстонки", "action_flag": 2, "change_message": "[{\"changed\": {\"fields\": [\"Slug\"]}}]"}}, {"model": "admin.logentry", "pk": 39, "fields": {"action_time": "2023-10-29T14:09:40.646Z", "user": 1, "content_type": 9, "object_id": "1", "object_repr": "блондинка", "action_flag": 1, "change_message": "[{\"added\": {}}]"}}, {"model": "admin.logentry", "pk": 40, "fields": {"action_time": "2023-10-29T14:10:13.726Z", "user": 1, "content_type": 9, "object_id": "2", "object_repr": "брюнетка", "action_flag": 1, "change_message": "[{\"added\": {}}]"}}, {"model": "admin.logentry", "pk": 41, "fields": {"action_time": "2023-10-29T14:10:27.705Z", "user": 1, "content_type": 9, "object_id": "3", "object_repr": "рыжая", "action_flag": 1, "change_message": "[{\"added\": {}}]"}}, {"model": "admin.logentry", "pk": 42, "fields": {"action_time": "2023-10-29T14:10:49.313Z", "user": 1, "content_type": 9, "object_id": "4", "object_repr": "высокая", "action_flag": 1, "change_message": "[{\"added\": {}}]"}}, {"model": "admin.logentry", "pk": 43, "fields": {"action_time": "2023-10-29T14:11:07.119Z", "user": 1, "content_type": 9, "object_id": "5", "object_repr": "низкая", "action_flag": 1, "change_message": "[{\"added\": {}}]"}}, {"model": "admin.logentry", "pk": 44, "fields": {"action_time": "2023-10-29T14:12:58.470Z", "user": 1, "content_type": 8, "object_id": "9", "object_repr": "Alex Grey", "action_flag": 2, "change_message": "[{\"changed\": {\"fields\": [\"\\u0421\\u0442\\u0430\\u0442\\u0443\\u0441\", \"Tags\"]}}]"}}, {"model": "admin.logentry", "pk": 45, "fields": {"action_time": "2023-10-29T14:13:18.513Z", "user": 1, "content_type": 8, "object_id": "1", "object_repr": "Alina Lopez", "action_flag": 2, "change_message": "[{\"changed\": {\"fields\": [\"\\u0421\\u0442\\u0430\\u0442\\u0443\\u0441\", \"Tags\"]}}]"}}, {"model": "admin.logentry", "pk": 46, "fields": {"action_time": "2023-10-29T14:13:38.900Z", "user": 1, "content_type": 8, "object_id": "17", "object_repr": "Amy Pink", "action_flag": 2, "change_message": "[{\"changed\": {\"fields\": [\"\\u0421\\u0442\\u0430\\u0442\\u0443\\u0441\", \"Tags\"]}}]"}}, {"model": "admin.logentry", "pk": 47, "fields": {"action_time": "2023-10-29T14:14:14.133Z", "user": 1, "content_type": 8, "object_id": "7", "object_repr": "Cherry Kiss", "action_flag": 2, "change_message": "[{\"changed\": {\"fields\": [\"\\u0421\\u0442\\u0430\\u0442\\u0443\\u0441\", \"Tags\"]}}]"}}, {"model": "admin.logentry", "pk": 48, "fields": {"action_time": "2023-10-29T14:14:23.780Z", "user": 1, "content_type": 8, "object_id": "9", "object_repr": "Alex Grey", "action_flag": 2, "change_message": "[{\"changed\": {\"fields\": [\"\\u0421\\u0442\\u0430\\u0442\\u0443\\u0441\"]}}]"}}, {"model": "admin.logentry", "pk": 49, "fields": {"action_time": "2023-10-29T14:14:29.776Z", "user": 1, "content_type": 8, "object_id": "1", "object_repr": "Alina Lopez", "action_flag": 2, "change_message": "[{\"changed\": {\"fields\": [\"\\u0421\\u0442\\u0430\\u0442\\u0443\\u0441\"]}}]"}}, {"model": "admin.logentry", "pk": 50, "fields": {"action_time": "2023-10-29T14:14:38.663Z", "user": 1, "content_type": 8, "object_id": "17", "object_repr": "Amy Pink", "action_flag": 2, "change_message": "[{\"changed\": {\"fields\": [\"\\u0421\\u0442\\u0430\\u0442\\u0443\\u0441\"]}}]"}}, {"model": "admin.logentry", "pk": 51, "fields": {"action_time": "2023-10-29T14:14:43.704Z", "user": 1, "content_type": 8, "object_id": "7", "object_repr": "Cherry Kiss", "action_flag": 2, "change_message": "[{\"changed\": {\"fields\": [\"\\u0421\\u0442\\u0430\\u0442\\u0443\\u0441\"]}}]"}}, {"model": "admin.logentry", "pk": 52, "fields": {"action_time": "2023-10-29T14:15:11.202Z", "user": 1, "content_type": 8, "object_id": "2", "object_repr": "dollhole", "action_flag": 2, "change_message": "[{\"changed\": {\"fields\": [\"Tags\"]}}]"}}, {"model": "admin.logentry", "pk": 53, "fields": {"action_time": "2023-10-29T14:15:57.349Z", "user": 1, "content_type": 8, "object_id": "4", "object_repr": "Eva Elfie", "action_flag": 2, "change_message": "[{\"changed\": {\"fields\": [\"Tags\"]}}]"}}, {"model": "admin.logentry", "pk": 54, "fields": {"action_time": "2023-10-29T14:16:18.774Z", "user": 1, "content_type": 8, "object_id": "18", "object_repr": "Haley Reed", "action_flag": 2, "change_message": "[{\"changed\": {\"fields\": [\"Tags\"]}}]"}}, {"model": "admin.logentry", "pk": 55, "fields": {"action_time": "2023-10-29T14:16:42.924Z", "user": 1, "content_type": 8, "object_id": "5", "object_repr": "Hong Kong Doll", "action_flag": 2, "change_message": "[{\"changed\": {\"fields\": [\"Tags\"]}}]"}}, {"model": "admin.logentry", "pk": 56, "fields": {"action_time": "2023-10-29T14:17:19.262Z", "user": 1, "content_type": 8, "object_id": "16", "object_repr": "Jada Stevens", "action_flag": 2, "change_message": "[{\"changed\": {\"fields\": [\"Tags\"]}}]"}}, {"model": "admin.logentry", "pk": 57, "fields": {"action_time": "2023-10-29T14:17:42.877Z", "user": 1, "content_type": 8, "object_id": "20", "object_repr": "Katerina Hartlova", "action_flag": 2, "change_message": "[{\"changed\": {\"fields\": [\"Tags\"]}}]"}}, {"model": "admin.logentry", "pk": 58, "fields": {"action_time": "2023-10-29T14:18:07.468Z", "user": 1, "content_type": 8, "object_id": "8", "object_repr": "Little Caprice", "action_flag": 2, "change_message": "[{\"changed\": {\"fields\": [\"Tags\"]}}]"}}, {"model": "admin.logentry", "pk": 59, "fields": {"action_time": "2023-10-29T14:18:29.308Z", "user": 1, "content_type": 8, "object_id": "14", "object_repr": "Lola Fae", "action_flag": 2, "change_message": "[{\"changed\": {\"fields\": [\"Tags\"]}}]"}}, {"model": "admin.logentry", "pk": 60, "fields": {"action_time": "2023-10-29T14:19:10.729Z", "user": 1, "content_type": 8, "object_id": "6", "object_repr": "Solazola", "action_flag": 2, "change_message": "[{\"changed\": {\"fields\": [\"Tags\"]}}]"}}, {"model": "admin.logentry", "pk": 61, "fields": {"action_time": "2023-10-29T14:20:02.076Z", "user": 1, "content_type": 8, "object_id": "19", "object_repr": "Nessa Devil", "action_flag": 2, "change_message": "[{\"changed\": {\"fields\": [\"Tags\"]}}]"}}, {"model": "admin.logentry", "pk": 62, "fields": {"action_time": "2023-10-29T14:20:21.256Z", "user": 1, "content_type": 8, "object_id": "15", "object_repr": "Princess Clover", "action_flag": 2, "change_message": "[{\"changed\": {\"fields\": [\"Tags\"]}}]"}}, {"model": "admin.logentry", "pk": 63, "fields": {"action_time": "2023-10-29T14:20:47.789Z", "user": 1, "content_type": 8, "object_id": "10", "object_repr": "Rachel Rivers", "action_flag": 2, "change_message": "[{\"changed\": {\"fields\": [\"Tags\"]}}]"}}, {"model": "admin.logentry", "pk": 64, "fields": {"action_time": "2023-10-29T14:21:26.890Z", "user": 1, "content_type": 8, "object_id": "21", "object_repr": "Riley Reid", "action_flag": 2, "change_message": "[{\"changed\": {\"fields\": [\"Tags\"]}}]"}}, {"model": "admin.logentry", "pk": 65, "fields": {"action_time": "2023-10-29T14:25:43.458Z", "user": 1, "content_type": 8, "object_id": "22", "object_repr": "Lina Diamond", "action_flag": 1, "change_message": "[{\"added\": {}}]"}}, {"model": "admin.logentry", "pk": 66, "fields": {"action_time": "2023-10-29T14:26:26.483Z", "user": 1, "content_type": 8, "object_id": "23", "object_repr": "Elin Flame", "action_flag": 1, "change_message": "[{\"added\": {}}]"}}, {"model": "admin.logentry", "pk": 67, "fields": {"action_time": "2023-10-29T14:27:50.991Z", "user": 1, "content_type": 8, "object_id": "24", "object_repr": "Liis Lass", "action_flag": 1, "change_message": "[{\"added\": {}}]"}}, {"model": "admin.logentry", "pk": 68, "fields": {"action_time": "2023-10-29T14:28:32.426Z", "user": 1, "content_type": 8, "object_id": "25", "object_repr": "Triinu Hoolma", "action_flag": 1, "change_message": "[{\"added\": {}}]"}}, {"model": "admin.logentry", "pk": 69, "fields": {"action_time": "2023-10-29T14:29:05.479Z", "user": 1, "content_type": 8, "object_id": "3", "object_repr": "Mini Diva", "action_flag": 2, "change_message": "[{\"changed\": {\"fields\": [\"Tags\"]}}]"}}, {"model": "admin.logentry", "pk": 70, "fields": {"action_time": "2023-10-29T14:29:42.799Z", "user": 1, "content_type": 8, "object_id": "12", "object_repr": "Tiffany Thompson", "action_flag": 2, "change_message": "[{\"changed\": {\"fields\": [\"Tags\"]}}]"}}, {"model": "admin.logentry", "pk": 71, "fields": {"action_time": "2023-10-29T14:30:06.309Z", "user": 1, "content_type": 8, "object_id": "13", "object_repr": "Valerie Steele", "action_flag": 2, "change_message": "[{\"changed\": {\"fields\": [\"Tags\"]}}]"}}, {"model": "admin.logentry", "pk": 72, "fields": {"action_time": "2023-10-29T14:30:25.614Z", "user": 1, "content_type": 8, "object_id": "11", "object_repr": "Vanessa Decker", "action_flag": 2, "change_message": "[{\"changed\": {\"fields\": [\"Tags\"]}}]"}}, {"model": "admin.logentry", "pk": 73, "fields": {"action_time": "2023-10-29T15:43:38.759Z", "user": 1, "content_type": 8, "object_id": "26", "object_repr": "Abigaile Johnson", "action_flag": 1, "change_message": "[{\"added\": {}}]"}}, {"model": "admin.logentry", "pk": 74, "fields": {"action_time": "2023-10-29T15:44:18.224Z", "user": 1, "content_type": 8, "object_id": "27", "object_repr": "Ria Sunn", "action_flag": 1, "change_message": "[{\"added\": {}}]"}}, {"model": "admin.logentry", "pk": 75, "fields": {"action_time": "2023-10-29T15:45:23.569Z", "user": 1, "content_type": 8, "object_id": "28", "object_repr": "Fia Murr", "action_flag": 1, "change_message": "[{\"added\": {}}]"}}, {"model": "admin.logentry", "pk": 76, "fields": {"action_time": "2023-10-29T17:52:06.755Z", "user": 1, "content_type": 8, "object_id": "29", "object_repr": "Zhang Xin Yu", "action_flag": 1, "change_message": "[{\"added\": {}}]"}}, {"model": "admin.logentry", "pk": 77, "fields": {"action_time": "2023-10-29T17:53:12.032Z", "user": 1, "content_type": 8, "object_id": "30", "object_repr": "Angela Zhou", "action_flag": 1, "change_message": "[{\"added\": {}}]"}}, {"model": "admin.logentry", "pk": 78, "fields": {"action_time": "2023-10-29T17:53:48.991Z", "user": 1, "content_type": 8, "object_id": "31", "object_repr": "Huang Yi Lin", "action_flag": 1, "change_message": "[{\"added\": {}}]"}}, {"model": "admin.logentry", "pk": 79, "fields": {"action_time": "2023-10-29T17:54:29.574Z", "user": 1, "content_type": 8, "object_id": "32", "object_repr": "Qing Chu", "action_flag": 1, "change_message": "[{\"added\": {}}]"}}, {"model": "admin.logentry", "pk": 80, "fields": {"action_time": "2023-10-29T17:55:41.435Z", "user": 1, "content_type": 8, "object_id": "33", "object_repr": "Gabbie Carter", "action_flag": 1, "change_message": "[{\"added\": {}}]"}}, {"model": "admin.logentry", "pk": 81, "fields": {"action_time": "2023-10-29T19:52:07.627Z", "user": 1, "content_type": 8, "object_id": "30", "object_repr": "Angela Zhou", "action_flag": 2, "change_message": "[{\"changed\": {\"fields\": [\"\\u0421\\u043e\\u0434\\u0435\\u0440\\u0436\\u0430\\u043d\\u0438\\u0435\", \"\\u0421\\u0442\\u0430\\u0442\\u0443\\u0441\"]}}]"}}, {"model": "admin.logentry", "pk": 82, "fields": {"action_time": "2023-10-29T19:52:16.660Z", "user": 1, "content_type": 8, "object_id": "30", "object_repr": "Angela Zhou", "action_flag": 2, "change_message": "[{\"changed\": {\"fields\": [\"\\u0421\\u0442\\u0430\\u0442\\u0443\\u0441\"]}}]"}}, {"model": "admin.logentry", "pk": 83, "fields": {"action_time": "2023-11-03T13:27:09.549Z", "user": 1, "content_type": 8, "object_id": "41", "object_repr": "Maniac Alisa", "action_flag": 3, "change_message": ""}}, {"model": "admin.logentry", "pk": 84, "fields": {"action_time": "2023-11-03T13:27:09.553Z", "user": 1, "content_type": 8, "object_id": "34", "object_repr": "11", "action_flag": 3, "change_message": ""}}, {"model": "admin.logentry", "pk": 85, "fields": {"action_time": "2023-11-03T13:28:58.781Z", "user": 1, "content_type": 8, "object_id": "43", "object_repr": "Maniac Alisa", "action_flag": 2, "change_message": "[{\"changed\": {\"fields\": [\"\\u0424\\u043e\\u0442\\u043e\\u0433\\u0440\\u0430\\u0444\\u0438\\u044f\", \"Tags\"]}}]"}}, {"model": "admin.logentry", "pk": 86, "fields": {"action_time": "2023-11-04T13:16:25.009Z", "user": 1, "content_type": 8, "object_id": "45", "object_repr": "sdghdg", "action_flag": 3, "change_message": ""}}, {"model": "admin.logentry", "pk": 87, "fields": {"action_time": "2023-11-04T13:16:25.013Z", "user": 1, "content_type": 8, "object_id": "44", "object_repr": "ghjdthrf", "action_flag": 3, "change_message": ""}}, {"model": "admin.logentry", "pk": 88, "fields": {"action_time": "2023-11-04T13:50:35.989Z", "user": 1, "content_type": 8, "object_id": "46", "object_repr": "agsfdgs", "action_flag": 3, "change_message": ""}}, {"model": "admin.logentry", "pk": 89, "fields": {"action_time": "2023-11-04T13:54:52.901Z", "user": 1, "content_type": 8, "object_id": "47", "object_repr": "", "action_flag": 3, "change_message": ""}}, {"model": "admin.logentry", "pk": 90, "fields": {"action_time": "2023-11-04T13:55:58.683Z", "user": 1, "content_type": 8, "object_id": "50", "object_repr": "", "action_flag": 3, "change_message": ""}}, {"model": "admin.logentry", "pk": 91, "fields": {"action_time": "2023-11-04T13:57:29.396Z", "user": 1, "content_type": 8, "object_id": "51", "object_repr": "agsfdgsty1", "action_flag": 3, "change_message": ""}}, {"model": "admin.logentry", "pk": 92, "fields": {"action_time": "2023-11-04T15:09:53.539Z", "user": 1, "content_type": 8, "object_id": "52", "object_repr": "agsfdgsty1", "action_flag": 3, "change_message": ""}}, {"model": "admin.logentry", "pk": 93, "fields": {"action_time": "2023-11-06T09:50:41.531Z", "user": 1, "content_type": 8, "object_id": "53", "object_repr": "sdfasaf", "action_flag": 3, "change_message": ""}}, {"model": "admin.logentry", "pk": 94, "fields": {"action_time": "2023-11-08T08:47:21.063Z", "user": 1, "content_type": 8, "object_id": "26", "object_repr": "Abigaile Johnso", "action_flag": 2, "change_message": "[{\"changed\": {\"fields\": [\"\\u0417\\u0430\\u0433\\u043e\\u043b\\u043e\\u0432\\u043e\\u043a\"]}}]"}}, {"model": "admin.logentry", "pk": 95, "fields": {"action_time": "2023-11-08T08:47:35.849Z", "user": 1, "content_type": 8, "object_id": "26", "object_repr": "Abigaile Johnson", "action_flag": 2, "change_message": "[{\"changed\": {\"fields\": [\"\\u0417\\u0430\\u0433\\u043e\\u043b\\u043e\\u0432\\u043e\\u043a\"]}}]"}}, {"model": "admin.logentry", "pk": 96, "fields": {"action_time": "2023-11-09T13:10:21.933Z", "user": 1, "content_type": 8, "object_id": "57", "object_repr": "dfgdgdfgds", "action_flag": 3, "change_message": ""}}, {"model": "admin.logentry", "pk": 97, "fields": {"action_time": "2023-11-09T13:10:21.940Z", "user": 1, "content_type": 8, "object_id": "56", "object_repr": "eeeeee", "action_flag": 3, "change_message": ""}}, {"model": "admin.logentry", "pk": 98, "fields": {"action_time": "2023-11-09T13:10:21.944Z", "user": 1, "content_type": 8, "object_id": "55", "object_repr": "dgdsf", "action_flag": 3, "change_message": ""}}, {"model": "admin.logentry", "pk": 99, "fields": {"action_time": "2023-12-16T15:34:39.772Z", "user": 1, "content_type": 8, "object_id": "58", "object_repr": "fdgdsgdg", "action_flag": 3, "change_message": ""}}, {"model": "auth.user", "pk": 1, "fields": {"password": "pbkdf2_sha256$600000$lXxJF8q5u3YmH40w4ek1D3$wIB7WRJHNpGBowI8zWzGCtyDQqE/GLioQz9mkJr/Fes=", "last_login": "2023-12-16T15:05:22.539Z", "is_superuser": true, "username": "lilyxer", "first_name": "", "last_name": "", "email": "", "is_staff": true, "is_active": true, "date_joined": "2023-10-27T14:03:30.525Z", "groups": [], "user_permissions": []}}, {"model": "auth.user", "pk": 2, "fields": {"password": "pbkdf2_sha256$600000$uEfM9f2b2EO02hSWehydPO$4ntPyW0UIZ7clzGN21za0qL/UxmdhjuMai4ifNurRZ8=", "last_login": "2023-12-17T12:58:37.468Z", "is_superuser": false, "username": "user1", "first_name": "Mike", "last_name": "Bor", "email": "user1@women.ru", "is_staff": false, "is_active": true, "date_joined": "2023-12-17T12:58:26.865Z", "groups": [], "user_permissions": []}}, {"model": "sessions.session", "pk": "j2nh6ms0inzmj3gne2ehwzc0fk44n5ug", "fields": {"session_data": ".eJxVjDsOwjAQRO_iGlnyd21Kes5g7fqDA8iW4qSKuDuJlALKmfdmNhZwXWpYR57DlNiVCXb57QjjK7cDpCe2R-ext2WeiB8KP-ng957y-3a6fwcVR93XxmmpTM4AVjoSIuk9-GwBlVKuWA9UtCukNUJC6YqXgJZEtNaQBM0-X8tNN2Q:1qwNRa:XUGl3z6inKAz8YKTkrNgdoT7srZxz2w00vjV2jWxyJI", "expire_date": "2023-11-10T14:04:10.759Z"}}, {"model": "sessions.session", "pk": "kq8ev1vvq8ol8g82487mip17i03wk8y7", "fields": {"session_data": ".eJxVjLsOAiEUBf-F2hDeD0v7_QZygYusGkiW3cr474ZkC23PzJw3CXDsNRwDt7BmciWCXH63COmJbYL8gHbvNPW2b2ukU6EnHXTpGV-30_07qDDqrBVKxZ2KmgP3SmdvrBbGF8a81AjKGmERAVMpWjEWhXaSJ1dc9Ba8IJ8vwMo3Jg:1rEqj7:Kb_g-Y485AlPt4eiHybnk9rGtNLbY2z0tZFLLug2fEU", "expire_date": "2023-12-31T12:58:37.491Z"}}, {"model": "women.women", "pk": 1, "fields": {"title": "Alina Lopez", "slug": "alina-lopez", "content": "Alina Lopez Порно актриса родом из США родилась 06.09.1995. В настоящее время она участвовала в 79 съемках видео и 238 фотосетах.Актриса занимает 14 место в пользовательском рейтинге. В данный момент она активна, а это значит, что на все еще снимается в видео и делает фотосессии. Девушка так же любит татуировки. Имеет пирсинг.", "time_create": "2023-10-27T14:39:04.000Z", "time_update": "2023-10-29T14:14:29.770Z", "is_published": true, "photo": "photos/Alina_Lopez.png", "cat": 1, "author": 1, "tags": [2, 5]}}, {"model": "women.women", "pk": 2, "fields": {"title": "dollhole", "slug": "dollhole", "content": "dollhole Порно актриса родом из Россия родилась 11.11.2000. В настоящее время она участвовала в 6 съемках видео и 15 фотосетах.Актриса занимает 22 место в пользовательском рейтинге. В данный момент она активна, а это значит, что на все еще снимается в видео и делает фотосессии. Девушка так же любит татуировки. Имеет пирсинг на No", "time_create": "2023-10-27T14:40:58.457Z", "time_update": "2023-10-29T14:15:11.191Z", "is_published": true, "photo": "photos/dollhole.png", "cat": 2, "author": 1, "tags": [1, 5]}}, {"model": "women.women", "pk": 3, "fields": {"title": "Mini Diva", "slug": "mini-diva", "content": "Mini Diva Порно актриса родом из Чехия. Актриса занимает 11 место в пользовательском рейтинге. В данный момент она активна, а это значит, что на все еще снимается в видео и делает фотосессии. Девушка так же любит татуировки. Имеет пирсинг на Yes", "time_create": "2023-10-27T14:41:56.996Z", "time_update": "2023-10-29T14:29:05.473Z", "is_published": true, "photo": "photos/Mini_Diva.png", "cat": 3, "author": 1, "tags": [2, 5]}}, {"model": "women.women", "pk": 4, "fields": {"title": "Eva Elfie", "slug": "eva-elfie", "content": "Eva Elfie Порно актриса родом из Россия родилась 27.05.2000. В настоящее время она участвовала в 27 съемках видео и 127 фотосетах.Актриса занимает 65566 место в пользовательском рейтинге. В данный момент она активна, а это значит, что на все еще снимается в видео и делает фотосессии. Девушка так же любит татуировки. Имеет пирсинг на Yes", "time_create": "2023-10-27T14:42:28.973Z", "time_update": "2023-10-29T14:15:57.342Z", "is_published": true, "photo": "photos/Eva_Elfie.png", "cat": 2, "author": 1, "tags": [1, 5]}}, {"model": "women.women", "pk": 5, "fields": {"title": "Hong Kong Doll", "slug": "hong-kong-doll", "content": "Hong Kong Doll Порно актриса родом из Китай (Китайская Народная Республика) родилась 01.08.1994. Актриса занимает 7 место в пользовательском рейтинге. В данный момент она активна, а это значит, что на все еще снимается в видео и делает фотосессии. Девушка так же любит татуировки. Имеет пирсинг на Yes", "time_create": "2023-10-27T14:43:20.294Z", "time_update": "2023-10-29T14:16:42.917Z", "is_published": true, "photo": "photos/Hong_Kong_Doll.png", "cat": 4, "author": 1, "tags": [2, 5]}}, {"model": "women.women", "pk": 6, "fields": {"title": "Solazola", "slug": "solazola", "content": "Solazola Порно актриса родом из Эстония. Актриса занимает 12 место в пользовательском рейтинге. В данный момент она активна, а это значит, что на все еще снимается в видео и делает фотосессии. Девушка так же любит татуировки. Имеет пирсинг на No", "time_create": "2023-10-27T14:44:00.299Z", "time_update": "2023-10-29T14:19:10.718Z", "is_published": true, "photo": "photos/Solazola.png", "cat": 5, "author": 1, "tags": [2, 4]}}, {"model": "women.women", "pk": 7, "fields": {"title": "Cherry Kiss", "slug": "cherry-kiss", "content": "Cherry Kiss Порно актриса родом из Сербия родилась 31.12.1992. В настоящее время она участвовала в 94 съемках видео и 507 фотосетах.Актриса занимает 3 место в пользовательском рейтинге. В данный момент она активна, а это значит, что на все еще снимается в видео и делает фотосессии. Девушка так же любит татуировки. Имеет пирсинг на Пупке", "time_create": "2023-10-27T14:47:06.004Z", "time_update": "2023-10-29T14:14:43.700Z", "is_published": true, "photo": "photos/Cherry_Kiss.png", "cat": 2, "author": 1, "tags": [1, 4]}}, {"model": "women.women", "pk": 8, "fields": {"title": "Little Caprice", "slug": "little-caprice", "content": "Little Caprice Порно актриса родом из Чехия родилась 26.10.1988. В настоящее время она участвовала в 51 съемках видео и 412 фотосетах.Актриса занимает 681 место в пользовательском рейтинге. В данный момент она активна, а это значит, что на все еще снимается в видео и делает фотосессии. Девушка так же любит татуировки. Имеет пирсинг на Языке; Носу; Пупке", "time_create": "2023-10-27T14:47:46.333Z", "time_update": "2023-10-29T14:18:07.459Z", "is_published": true, "photo": "photos/Little_Caprice.png", "cat": 3, "author": 1, "tags": [2, 4]}}, {"model": "women.women", "pk": 9, "fields": {"title": "Alex Grey", "slug": "alex-grey", "content": "Alex Grey Откровенная модель родом из США родилась 20.04.1996. В настоящее время она участвовала в 77 съемках видео и 336 фотосетах.Актриса занимает 649 место в пользовательском рейтинге. В данный момент она активна, а это значит, что на все еще снимается в видео и делает фотосессии. Девушка так же любит татуировки. Имеет пирсинг на Пупке; Языке", "time_create": "2023-10-27T14:48:18.334Z", "time_update": "2023-10-29T14:14:23.772Z", "is_published": true, "photo": "photos/Alex_Grey.png", "cat": 1, "author": 1, "tags": [1, 5]}}, {"model": "women.women", "pk": 10, "fields": {"title": "Rachel Rivers", "slug": "rachel-rivers", "content": "Rachel Rivers Порно актриса родом из США родилась 20.01.2000. В настоящее время она участвовала в 12 съемках видео и 33 фотосетах.Актриса занимает 130 место в пользовательском рейтинге. В данный момент она активна, а это значит, что на все еще снимается в видео и делает фотосессии.", "time_create": "2023-10-28T19:07:44.334Z", "time_update": "2023-10-29T14:20:47.783Z", "is_published": true, "photo": "photos/Rachel_Rivers.png", "cat": 1, "author": 1, "tags": [2, 5]}}, {"model": "women.women", "pk": 11, "fields": {"title": "Vanessa Decker", "slug": "vanessa-decker", "content": "Vanessa Decker Порно актриса родом из Чехия родилась 02.01.1995. В настоящее время она участвовала в 46 съемках видео и 360 фотосетах.Актриса занимает 928 место в пользовательском рейтинге. В данный момент она активна, а это значит, что на все еще снимается в видео и делает фотосессии. Девушка так же любит татуировки. Имеет пирсинг на Пупке", "time_create": "2023-10-28T19:09:22.814Z", "time_update": "2023-10-29T14:30:25.601Z", "is_published": true, "photo": "photos/Vanessa_Decker.png", "cat": 3, "author": 1, "tags": [2, 4]}}, {"model": "women.women", "pk": 12, "fields": {"title": "Tiffany Thompson", "slug": "tiffany-thompson", "content": "Tiffany Thompson Порно актриса родом из США родилась 25.07.1992. В настоящее время она участвовала в 23 съемках видео и 273 фотосетах.Актриса занимает 2431 место в пользовательском рейтинге. В данный момент она завершила карьеру, а это значит, что уже не работает в данной профессии. Девушка так же любит татуировки. Имеет пирсинг на Пупке", "time_create": "2023-10-28T19:11:25.536Z", "time_update": "2023-10-29T14:29:42.795Z", "is_published": true, "photo": "photos/Tiffany_Thompson.png", "cat": 1, "author": 1, "tags": [2, 4]}}, {"model": "women.women", "pk": 13, "fields": {"title": "Valerie Steele", "slug": "valerie-steele", "content": "Valerie Steele Порно актриса родом из США родилась 12.06.1999. В настоящее время она участвовала в 2 съемках видео и 12 фотосетах.Актриса занимает 2795 место в пользовательском рейтинге. В данный момент она активна, а это значит, что на все еще снимается в видео и делает фотосессии. Девушка так же любит татуировки. Имеет пирсинг на Разные", "time_create": "2023-10-28T19:13:14.597Z", "time_update": "2023-10-29T14:30:06.304Z", "is_published": true, "photo": "photos/Valerie_Steele.png", "cat": 1, "author": 1, "tags": [2, 5]}}, {"model": "women.women", "pk": 14, "fields": {"title": "Lola Fae", "slug": "lola-fae", "content": "Lola Fae Порно актриса родом из США родилась 13.05.1996. В настоящее время она участвовала в 30 съемках видео и 98 фотосетах.Актриса занимает 726 место в пользовательском рейтинге. В данный момент она активна, а это значит, что на все еще снимается в видео и делает фотосессии. Имеет пирсинг на Нижней губе;Сосках;Правой ноздре", "time_create": "2023-10-28T19:13:58.884Z", "time_update": "2023-10-29T14:18:29.288Z", "is_published": true, "photo": "photos/Lola_Fae.png", "cat": 1, "author": 1, "tags": [5, 3]}}, {"model": "women.women", "pk": 15, "fields": {"title": "Princess Clover", "slug": "princess-clover", "content": "Princess Clover Порно актриса родом из Россия родилась 12.11.1989. В настоящее время она участвовала в 26 съемках видео и 331 фотосетах.Актриса занимает 1193 место в пользовательском рейтинге. В данный момент она активна, а это значит, что на все еще снимается в видео и делает фотосессии. Девушка так же любит татуировки.", "time_create": "2023-10-28T19:15:26.917Z", "time_update": "2023-10-29T14:20:21.250Z", "is_published": true, "photo": "photos/Princess_Clover.png", "cat": 2, "author": 1, "tags": [5, 3]}}, {"model": "women.women", "pk": 16, "fields": {"title": "Jada Stevens", "slug": "jada-stevens", "content": "Jada Stevens Порно актриса родом из США родилась 04.07.1988. В настоящее время она участвовала в 135 съемках видео и 749 фотосетах.Актриса занимает 103 место в пользовательском рейтинге. В данный момент она активна, а это значит, что на все еще снимается в видео и делает фотосессии. Девушка так же любит татуировки. Имеет пирсинг на Пупке; Левой ноздре; Клиторе; Taint", "time_create": "2023-10-28T19:16:07.066Z", "time_update": "2023-10-29T14:17:19.258Z", "is_published": true, "photo": "photos/Jada_Stevens.png", "cat": 1, "author": 1, "tags": [2, 5]}}, {"model": "women.women", "pk": 17, "fields": {"title": "Amy Pink", "slug": "amy-pink", "content": "Amy Pink Порно актриса родом из Чехия родилась 23.07.1988. В настоящее время она участвовала в 45 съемках видео и 269 фотосетах.Актриса занимает 638 место в пользовательском рейтинге. В данный момент она активна, а это значит, что на все еще снимается в видео и делает фотосессии.", "time_create": "2023-10-28T19:17:43.431Z", "time_update": "2023-10-29T14:14:38.657Z", "is_published": true, "photo": "photos/Amy_Pink.png", "cat": 3, "author": 1, "tags": [1, 5]}}, {"model": "women.women", "pk": 18, "fields": {"title": "Haley Reed", "slug": "haley-reed", "content": "Haley Reed Порно актриса родом из США родилась 20.12.1996. В настоящее время она участвовала в 93 съемках видео и 333 фотосетах.Актриса занимает 642 место в пользовательском рейтинге. В данный момент она активна, а это значит, что на все еще снимается в видео и делает фотосессии. Девушка так же любит татуировки. Имеет пирсинг на Nipple Rings; Перегородке", "time_create": "2023-10-28T19:18:19.669Z", "time_update": "2023-10-29T14:16:18.770Z", "is_published": true, "photo": "photos/Haley_Reed.png", "cat": 1, "author": 1, "tags": [1, 4]}}, {"model": "women.women", "pk": 19, "fields": {"title": "Nessa Devil", "slug": "nessa-devil", "content": "Nessa Devil Порно актриса родом из Чехия родилась 09.12.1988. В настоящее время она участвовала в 34 съемках видео и 206 фотосетах.Актриса занимает 1256 место в пользовательском рейтинге. В данный момент она активна, а это значит, что на все еще снимается в видео и делает фотосессии. Имеет пирсинг на Пупке", "time_create": "2023-10-28T19:19:00.283Z", "time_update": "2023-10-29T14:20:02.068Z", "is_published": true, "photo": "photos/Nessa_Devil.png", "cat": 3, "author": 1, "tags": [2, 4]}}, {"model": "women.women", "pk": 20, "fields": {"title": "Katerina Hartlova", "slug": "katerina-hartlova", "content": "Katerina Hartlova Порно актриса родом из Чехия родилась 19.09.1985. В настоящее время она участвовала в 64 съемках видео и 362 фотосетах.Актриса занимает 439 место в пользовательском рейтинге. В данный момент она активна, а это значит, что на все еще снимается в видео и делает фотосессии. Имеет пирсинг на Пупке; Ушах", "time_create": "2023-10-28T19:19:35.534Z", "time_update": "2023-10-29T14:17:42.871Z", "is_published": true, "photo": "photos/Katerina_Hartlova.png", "cat": 3, "author": 1, "tags": [1, 4]}}, {"model": "women.women", "pk": 21, "fields": {"title": "Riley Reid", "slug": "riley-reid", "content": "Riley Reid Порно актриса родом из США родилась 09.07.1991. В настоящее время она участвовала в 268 съемках видео и 1197 фотосетах.Актриса занимает 13 место в пользовательском рейтинге. В данный момент она завершила карьеру, а это значит, что уже не работает в данной профессии. Девушка так же любит татуировки.", "time_create": "2023-10-28T19:21:46.025Z", "time_update": "2023-10-29T14:21:26.885Z", "is_published": true, "photo": "photos/Riley_Reid.png", "cat": 1, "author": 1, "tags": [2, 5]}}, {"model": "women.women", "pk": 22, "fields": {"title": "Lina Diamond", "slug": "lina-diamond", "content": "Lina Diamond Откровенная модель родом из Эстония. Актриса занимает 12030 место в пользовательском рейтинге. В данный момент она активна, а это значит, что на все еще снимается в видео и делает фотосессии. Имеет пирсинг.", "time_create": "2023-10-29T14:25:43.453Z", "time_update": "2023-10-29T14:25:43.453Z", "is_published": true, "photo": "photos/Lina_Diamond.png", "cat": 5, "author": 1, "tags": [2, 4]}}, {"model": "women.women", "pk": 23, "fields": {"title": "Elin Flame", "slug": "elin-flame", "content": "Elin Flame Порно актриса родом из Эстония родилась 26.11.1996. В настоящее время она участвовала в 19 съемках видео и 68 фотосетах.Актриса занимает 2115 место в пользовательском рейтинге. В данный момент она активна, а это значит, что на все еще снимается в видео и делает фотосессии. Имеет пирсинг.", "time_create": "2023-10-29T14:26:26.474Z", "time_update": "2023-10-29T14:26:26.474Z", "is_published": true, "photo": "photos/Elin_Flame.png", "cat": 5, "author": 1, "tags": [4, 3]}}, {"model": "women.women", "pk": 24, "fields": {"title": "Liis Lass", "slug": "liis-lass", "content": "Liis Lass Актриса родом из Эстония. Актриса занимает 45322 место в пользовательском рейтинге.", "time_create": "2023-10-29T14:27:50.978Z", "time_update": "2023-10-29T14:27:50.978Z", "is_published": true, "photo": "photos/Liis_Lass.png", "cat": 5, "author": 1, "tags": [1, 4]}}, {"model": "women.women", "pk": 25, "fields": {"title": "Triinu Hoolma", "slug": "triinu-hoolma", "content": "Triinu Hoolma Фото-модель родом из Эстония. Актриса занимает 33831 место в пользовательском рейтинге. В данный момент она активна, а это значит, что на все еще снимается в видео и делает фотосессии. Имеет пирсинг.", "time_create": "2023-10-29T14:28:32.417Z", "time_update": "2023-10-29T14:28:32.417Z", "is_published": true, "photo": "photos/Triinu_Hoolma.png", "cat": 5, "author": 1, "tags": [1, 4]}}, {"model": "women.women", "pk": 26, "fields": {"title": "Abigaile Johnson", "slug": "abigaile-johnson", "content": "Abigaile Johnson Порно актриса родом из Чехия. В настоящее время она участвовала в 17 съемках видео и 224 фотосетах.Актриса занимает 2581 место в пользовательском рейтинге. В данный момент она завершила карьеру, а это значит, что уже не работает в данной профессии. Имеет пирсинг на Пупке; Языке", "time_create": "2023-10-29T15:43:38.752Z", "time_update": "2023-11-08T08:49:12.451Z", "is_published": true, "photo": "photos/Abigaile_Johnson.png", "cat": 3, "author": 1, "tags": [2, 5]}}, {"model": "women.women", "pk": 27, "fields": {"title": "Ria Sunn", "slug": "ria-sunn", "content": "Ria Sunn Порно актриса родом из Чехия родилась 21.11.1996. В настоящее время она участвовала в 39 съемках видео и 215 фотосетах.Актриса занимает 178 место в пользовательском рейтинге. В данный момент она активна, а это значит, что на все еще снимается в видео и делает фотосессии. Девушка так же любит татуировки.", "time_create": "2023-10-29T15:44:18.213Z", "time_update": "2023-10-29T15:44:18.213Z", "is_published": true, "photo": "photos/Ria_Sunn.png", "cat": 3, "author": 1, "tags": [1, 4]}}, {"model": "women.women", "pk": 28, "fields": {"title": "Fia Murr", "slug": "fia-murr", "content": "Fia Murr Порно актриса родом из Чехия родилась 15.08.1999. Актриса занимает 34208 место в пользовательском рейтинге.", "time_create": "2023-10-29T15:45:23.563Z", "time_update": "2023-10-29T15:45:23.563Z", "is_published": true, "photo": "photos/Fia_Murr.png", "cat": 3, "author": 1, "tags": [2, 4]}}, {"model": "women.women", "pk": 29, "fields": {"title": "Zhang Xin Yu", "slug": "zhang-xin-yu", "content": "Zhang Xin Yu Супермодель родом из Китай (Китайская Народная Республика) родилась 28.03.1987. Актриса занимает 45649 место в пользовательском рейтинге.", "time_create": "2023-10-29T17:52:06.749Z", "time_update": "2023-10-29T17:52:06.749Z", "is_published": true, "photo": "photos/Zhang_Xin_Yu.png", "cat": 4, "author": 1, "tags": [2, 4]}}, {"model": "women.women", "pk": 30, "fields": {"title": "Angela Zhou", "slug": "angela-zhou", "content": "Angela Zhou Актриса родом из Китай (Китайская Народная Республика). Актриса занимает 42353 место в пользовательском рейтинге.", "time_create": "2023-10-29T17:53:12.023Z", "time_update": "2023-10-29T19:52:16.655Z", "is_published": true, "photo": "photos/Angela_Zhou.png", "cat": 4, "author": 1, "tags": [2]}}, {"model": "women.women", "pk": 31, "fields": {"title": "Huang Yi Lin", "slug": "huang-yi-lin", "content": "Huang Yi Lin Супермодель родом из Китай (Китайская Народная Республика) родилась 02.05.1988. Актриса занимает 43930 место в пользовательском рейтинге.", "time_create": "2023-10-29T17:53:48.984Z", "time_update": "2023-10-29T17:53:48.984Z", "is_published": true, "photo": "photos/Huang_Yi_Lin.png", "cat": 4, "author": 1, "tags": [2, 4]}}, {"model": "women.women", "pk": 32, "fields": {"title": "Qing Chu", "slug": "qing-chu", "content": "Qing Chu Супермодель родом из Китай (Китайская Народная Республика) родилась 23.06.1988. Актриса занимает 45718 место в пользовательском рейтинге.", "time_create": "2023-10-29T17:54:29.567Z", "time_update": "2023-10-29T17:54:29.567Z", "is_published": true, "photo": "photos/Qing_Chu.png", "cat": 4, "author": 1, "tags": [2, 5]}}, {"model": "women.women", "pk": 33, "fields": {"title": "Gabbie Carter", "slug": "gabbie-carter", "content": "Gabbie Carter Порно актриса родом из США родилась 04.08.2000. В настоящее время она участвовала в 29 съемках видео и 116 фотосетах.Актриса занимает 173 место в пользовательском рейтинге. В данный момент она активна, а это значит, что на все еще снимается в видео и делает фотосессии. Девушка так же любит татуировки. Имеет пирсинг.", "time_create": "2023-10-29T17:55:41.429Z", "time_update": "2023-10-29T17:55:41.429Z", "is_published": true, "photo": "photos/Gabbie_Carter.png", "cat": 1, "author": 1, "tags": [1, 4]}}, {"model": "women.women", "pk": 43, "fields": {"title": "Maniac Alisa", "slug": "maniac-alisa", "content": "Maniac Alisa Порно актриса родом из Россия родилась 11.06.1995. В настоящее время она участвовала в 15 съемках видео и 40 фотосетах.Актриса занимает 30 место в пользовательском рейтинге. В данный момент она завершила карьеру, а это значит, что уже не работает в данной профессии. Девушка так же любит татуировки. Имеет пирсинг на Неизвестно", "time_create": "2023-11-03T13:27:34.055Z", "time_update": "2023-11-03T13:28:58.774Z", "is_published": true, "photo": "photos/Maniac_Alisa.png", "cat": 2, "author": 1, "tags": [2, 4]}}, {"model": "women.category", "pk": 1, "fields": {"name": "Американки", "slug": "usa"}}, {"model": "women.category", "pk": 2, "fields": {"name": "Русские", "slug": "rus"}}, {"model": "women.category", "pk": 3, "fields": {"name": "Чешки", "slug": "che"}}, {"model": "women.category", "pk": 4, "fields": {"name": "Китаянки", "slug": "chi"}}, {"model": "women.category", "pk": 5, "fields": {"name": "Эстонки", "slug": "ees"}}, {"model": "women.tagwomen", "pk": 1, "fields": {"title": "блондинка", "slug": "blond"}}, {"model": "women.tagwomen", "pk": 2, "fields": {"title": "брюнетка", "slug": "brune"}}, {"model": "women.tagwomen", "pk": 3, "fields": {"title": "рыжая", "slug": "red"}}, {"model": "women.tagwomen", "pk": 4, "fields": {"title": "высокая", "slug": "high"}}, {"model": "women.tagwomen", "pk": 5, "fields": {"title": "низкая", "slug": "low"}}]